jvlogger/__init__.py
jvlogger/__main__.py
jvlogger/cli.py
jvlogger/exceptions.py
jvlogger/formatters.py
jvlogger/hooks.py
jvlogger/jvlogger.py
jvlogger/lifecycle.py
jvlogger/logger_wrapper.py
jvlogger/signing.py
jvlogger/utils.py
jvlogger/verify.py
jvlogger/mutex/__init__.py
jvlogger/mutex/base.py
jvlogger/mutex/posix.py
jvlogger/mutex/windows.py
jvlogger-0.1.3.dist-info/licenses/LICENSE
jvlogger-0.1.3.dist-info/METADATA
jvlogger-0.1.3.dist-info/WHEEL
jvlogger-0.1.3.dist-info/top_level.txt
jvlogger-0.1.3.dist-info/RECORD
